{
  "parent": "simplycats:block/cat_bowl",
  "display": {
    "thirdperson_righthand": {
      "translation": [0, 5, -2]
    },
    "thirdperson_lefthand": {
      "translation": [0, 5, -2]
    },
    "firstperson_righthand": {
      "translation": [0, 5, -2]
    },
    "firstperson_lefthand": {
      "translation": [0, 5, -2]
    },
    "ground": {
      "translation": [0, 4, 0]
    },
    "gui": {
      "scale": [1.5, 1.5, 1.5],
      "translation": [0, 7, 0],
      "rotation": [16, 32, 0]
    }
  }
}